{"path":"C:\\Users\\任建一\\Desktop\\small_screw81-160\\093.png","outputs":{"object":[{"name":"0","bndbox":{"xmin":136,"ymin":240,"xmax":194,"ymax":300}},{"name":"0","bndbox":{"xmin":131,"ymin":365,"xmax":171,"ymax":407}},{"name":"0","bndbox":{"xmin":94,"ymin":885,"xmax":151,"ymax":925}},{"name":"0","bndbox":{"xmin":101,"ymin":947,"xmax":151,"ymax":990}},{"name":"0","bndbox":{"xmin":871,"ymin":235,"xmax":926,"ymax":310}},{"name":"1","bndbox":{"xmin":176,"ymin":815,"xmax":214,"ymax":865}},{"name":"1","bndbox":{"xmin":174,"ymin":1295,"xmax":214,"ymax":1347}},{"name":"1","bndbox":{"xmin":174,"ymin":1635,"xmax":221,"ymax":1685}},{"name":"1","bndbox":{"xmin":836,"ymin":825,"xmax":871,"ymax":885}},{"name":"1","bndbox":{"xmin":811,"ymin":1300,"xmax":846,"ymax":1375}},{"name":"1","bndbox":{"xmin":786,"ymin":1645,"xmax":831,"ymax":1707}},{"name":"2","bndbox":{"xmin":71,"ymin":1535,"xmax":141,"ymax":1595}}]},"time_labeled":1569328072526,"labeled":true,"size":{"width":1080,"height":1920,"depth":3}}