{"path":"C:\\Users\\任建一\\Desktop\\small_screw81-160\\153.png","outputs":{"object":[{"name":"0","bndbox":{"xmin":118,"ymin":231,"xmax":196,"ymax":304}},{"name":"0","bndbox":{"xmin":123,"ymin":354,"xmax":189,"ymax":418}},{"name":"0","bndbox":{"xmin":100,"ymin":863,"xmax":168,"ymax":927}},{"name":"0","bndbox":{"xmin":114,"ymin":950,"xmax":159,"ymax":995}},{"name":"0","bndbox":{"xmin":877,"ymin":254,"xmax":941,"ymax":318}},{"name":"1","bndbox":{"xmin":178,"ymin":815,"xmax":227,"ymax":880}},{"name":"1","bndbox":{"xmin":181,"ymin":1301,"xmax":224,"ymax":1352}},{"name":"1","bndbox":{"xmin":821,"ymin":824,"xmax":876,"ymax":895}},{"name":"1","bndbox":{"xmin":807,"ymin":1295,"xmax":855,"ymax":1384}},{"name":"1","bndbox":{"xmin":181,"ymin":1633,"xmax":224,"ymax":1704}},{"name":"1","bndbox":{"xmin":796,"ymin":1650,"xmax":835,"ymax":1712}},{"name":"2","bndbox":{"xmin":70,"ymin":1526,"xmax":150,"ymax":1606}}]},"time_labeled":1569329845208,"labeled":true,"size":{"width":1080,"height":1920,"depth":3}}