{"path":"D:\\small_screw161-240\\229.png","outputs":{"object":[{"name":"0","bndbox":{"xmin":151,"ymin":244,"xmax":191,"ymax":284}},{"name":"0","bndbox":{"xmin":882,"ymin":265,"xmax":917,"ymax":305}},{"name":"0","bndbox":{"xmin":143,"ymin":369,"xmax":184,"ymax":405}},{"name":"0","bndbox":{"xmin":119,"ymin":888,"xmax":151,"ymax":920}},{"name":"0","bndbox":{"xmin":119,"ymin":948,"xmax":152,"ymax":989}},{"name":"1","bndbox":{"xmin":175,"ymin":829,"xmax":203,"ymax":862}},{"name":"1","bndbox":{"xmin":843,"ymin":836,"xmax":874,"ymax":869}},{"name":"1","bndbox":{"xmin":180,"ymin":1303,"xmax":208,"ymax":1336}},{"name":"1","bndbox":{"xmin":818,"ymin":1321,"xmax":851,"ymax":1354}},{"name":"1","bndbox":{"xmin":181,"ymin":1653,"xmax":209,"ymax":1674}},{"name":"1","bndbox":{"xmin":808,"ymin":1663,"xmax":834,"ymax":1693}},{"name":"2","bndbox":{"xmin":90,"ymin":1551,"xmax":133,"ymax":1582}}]},"time_labeled":1569329106207,"labeled":true,"size":{"width":1080,"height":1920,"depth":3}}