{"path":"C:\\Users\\Administrator\\Desktop\\small_screw321-400\\349.png","outputs":{"object":[{"name":"2","bndbox":{"xmin":78,"ymin":1536,"xmax":130,"ymax":1584}},{"name":"0","bndbox":{"xmin":862,"ymin":243,"xmax":935,"ymax":304}},{"name":"0","bndbox":{"xmin":144,"ymin":229,"xmax":187,"ymax":288}},{"name":"0","bndbox":{"xmin":132,"ymin":356,"xmax":192,"ymax":411}},{"name":"0","bndbox":{"xmin":101,"ymin":879,"xmax":160,"ymax":929}},{"name":"0","bndbox":{"xmin":112,"ymin":947,"xmax":160,"ymax":995}},{"name":"1","bndbox":{"xmin":167,"ymin":809,"xmax":194,"ymax":865}},{"name":"1","bndbox":{"xmin":176,"ymin":1286,"xmax":207,"ymax":1352}},{"name":"1","bndbox":{"xmin":171,"ymin":1631,"xmax":205,"ymax":1686}},{"name":"1","bndbox":{"xmin":844,"ymin":825,"xmax":871,"ymax":879}},{"name":"1","bndbox":{"xmin":819,"ymin":1300,"xmax":851,"ymax":1365}},{"name":"1","bndbox":{"xmin":810,"ymin":1643,"xmax":835,"ymax":1704}}]},"time_labeled":1569328626158,"labeled":true,"size":{"width":1080,"height":1920,"depth":3}}