{"path":"C:\\Users\\Administrator\\Desktop\\small_screw321-400\\364.png","outputs":{"object":[{"name":"1","bndbox":{"xmin":166,"ymin":806,"xmax":205,"ymax":861}},{"name":"1","bndbox":{"xmin":170,"ymin":1293,"xmax":205,"ymax":1351}},{"name":"1","bndbox":{"xmin":170,"ymin":1644,"xmax":198,"ymax":1687}},{"name":"1","bndbox":{"xmin":841,"ymin":820,"xmax":872,"ymax":877}},{"name":"1","bndbox":{"xmin":821,"ymin":1312,"xmax":850,"ymax":1357}},{"name":"1","bndbox":{"xmin":803,"ymin":1644,"xmax":835,"ymax":1693}},{"name":"0","bndbox":{"xmin":858,"ymin":248,"xmax":921,"ymax":312}},{"name":"0","bndbox":{"xmin":143,"ymin":236,"xmax":178,"ymax":291}},{"name":"0","bndbox":{"xmin":131,"ymin":363,"xmax":174,"ymax":404}},{"name":"0","bndbox":{"xmin":111,"ymin":867,"xmax":158,"ymax":916}},{"name":"0","bndbox":{"xmin":113,"ymin":928,"xmax":152,"ymax":977}},{"name":"2","bndbox":{"xmin":78,"ymin":1548,"xmax":127,"ymax":1591}}]},"time_labeled":1569329259240,"labeled":true,"size":{"width":1080,"height":1920,"depth":3}}