{"path":"C:\\Users\\xiefight\\Desktop\\small_srew401-480\\446.png","outputs":{"object":[{"name":"0","bndbox":{"xmin":49,"ymin":232,"xmax":103,"ymax":280}},{"name":"0","bndbox":{"xmin":794,"ymin":238,"xmax":848,"ymax":298}},{"name":"0","bndbox":{"xmin":43,"ymin":358,"xmax":91,"ymax":406}},{"name":"0","bndbox":{"xmin":25,"ymin":875,"xmax":67,"ymax":917}},{"name":"0","bndbox":{"xmin":25,"ymin":941,"xmax":73,"ymax":989}},{"name":"1","bndbox":{"xmin":79,"ymin":809,"xmax":133,"ymax":851}},{"name":"1","bndbox":{"xmin":758,"ymin":821,"xmax":800,"ymax":875}},{"name":"1","bndbox":{"xmin":85,"ymin":1283,"xmax":127,"ymax":1337}},{"name":"1","bndbox":{"xmin":740,"ymin":1301,"xmax":782,"ymax":1355}},{"name":"1","bndbox":{"xmin":91,"ymin":1632,"xmax":127,"ymax":1680}},{"name":"1","bndbox":{"xmin":722,"ymin":1650,"xmax":770,"ymax":1692}},{"name":"2","bndbox":{"xmin":1,"ymin":1530,"xmax":49,"ymax":1578}}]},"time_labeled":1569331357045,"labeled":true,"size":{"width":1080,"height":1920,"depth":3}}